{"annotations": [{"id": "ba003ecd-b69f-43fe-a2b7-b31ad411fb3c", "page": 0, "label": {"text": "Textbox", "color": "#70DDBA"}, "bounds": {"left": 394.91200000000003, "top": -136.2928, "right": 394.91200000000003, "bottom": -136.2928}, "tokens": null}, {"id": "a609b7c1-aa4a-4ba3-b17d-6613b894a536", "page": 0, "label": {"text": "Textbox", "color": "#70DDBA"}, "bounds": {"left": 1033.2336, "top": 716.1856, "right": 1113.6608, "bottom": 740.7472}, "tokens": null}, {"id": "06d0288a-55e6-4fe2-991e-b7f93bdbf585", "page": 0, "label": {"text": "Textbox", "color": "#70DDBA"}, "bounds": {"left": 1094.8288, "top": 573.2464, "right": 1162.7344, "bottom": 614.1824}, "tokens": null}, {"id": "2c1aa8fc-d2bc-4c6a-89bd-f8f931e6d50c", "page": 0, "label": {"text": "Textbox", "color": "#70DDBA"}, "bounds": {"left": 1111.7952, "top": 579.9888, "right": 1176.8112, "bottom": 614.664}, "tokens": null}, {"id": "14c88e7b-2ec8-4d51-9bf7-953da1abf3bf", "page": 0, "label": {"text": "Textbox", "color": "#70DDBA"}, "bounds": {"left": 1215.28, "top": 578.3936, "right": 1336.6432, "bottom": 655.9312}, "tokens": null}, {"id": "4d7bed91-6845-4278-9214-9e8167dc0c8e", "page": 0, "label": {"text": "Textbox", "color": "#70DDBA"}, "bounds": {"left": 1544.6432, "top": 544.2032, "right": 1628.9232, "bottom": 642.9312}, "tokens": null}, {"id": "6aa43e2d-cb62-4d63-a8c5-8c078b0e037c", "page": 0, "label": {"text": "Textbox", "color": "#70DDBA"}, "bounds": {"left": 1364.8048, "top": 594.9456, "right": 1545.8864, "bottom": 718.2352000000001}, "tokens": null}, {"id": "67c89974-c9bd-41f0-853b-a5b5feac0206", "page": 0, "label": {"text": "Textbox", "color": "#70DDBA"}, "bounds": {"left": 1270.7952, "top": 376.20640000000003, "right": 1386.3792, "bottom": 492.27200000000005}, "tokens": null}, {"id": "620cfe42-187e-44b3-bdf9-32ca1f2be6b4", "page": 0, "label": {"text": "Textbox", "color": "#70DDBA"}, "bounds": {"left": 745.5264, "top": 351.42719999999997, "right": 939.1296, "bottom": 495.42560000000003}, "tokens": null}, {"id": "ffc793b1-01fb-449f-9ad6-4d807255971f", "page": 0, "label": {"text": "Textbox", "color": "#70DDBA"}, "bounds": {"left": 343.79200000000003, "top": 380.5408, "right": 470.9344, "bottom": 455.6704}, "tokens": null}, {"id": "62603485-6a3f-4e8b-8c8c-2441cf6691dc", "page": 0, "label": {"text": "Textbox", "color": "#70DDBA"}, "bounds": {"left": 752.7740119601328, "top": 440.8543734219269, "right": 902.5516119601328, "bottom": 558.846373421927}, "tokens": null}, {"id": "32ecada1-5fc9-4717-8a00-086bbbc78e12", "page": 0, "label": {"text": "Textbox", "color": "#70DDBA"}, "bounds": {"left": 959.0810471760798, "top": 315.89869501661127, "right": 1095.8554471760797, "bottom": 455.5626950166113}, "tokens": null}, {"id": "f950c5d1-f95c-4666-a1ff-380da5ccad90", "page": 0, "label": {"text": "Textbox", "color": "#70DDBA"}, "bounds": {"left": 1135.5523083056478, "top": 188.85846644518273, "right": 1239.0963083056479, "bottom": 302.0344664451827}, "tokens": null}, {"id": "e9c53431-888b-4617-9e7e-419915f46a7d", "page": 0, "label": {"text": "Textbox", "color": "#70DDBA"}, "bounds": {"left": 735.3892305647842, "top": 180.955673089701, "right": 837.9700305647841, "bottom": 298.947673089701}, "tokens": null}, {"id": "22cb5cac-4c37-49d3-9d43-31930b2e640d", "page": 0, "label": {"text": "Textbox", "color": "#70DDBA"}, "bounds": {"left": -183.47464186046508, "top": 156.89909900332228, "right": -11.543441860465009, "bottom": 268.1486990033223}, "tokens": null}, {"id": "3a242acf-7baf-4b5b-80a2-a8c3ad85bb17", "page": 0, "label": {"text": "Textbox", "color": "#70DDBA"}, "bounds": {"left": -194.8443162790697, "top": 311.98276677740864, "right": -69.62831627906968, "bottom": 417.93476677740864}, "tokens": null}], "relations": [{"sourceIds": ["d7070cab-99c8-40a4-9e3e-86fe8f011607", "6f3ae0c4-5f92-4282-9d1c-de543df1602c", "de3405f2-43c3-4980-8375-95742d15ebf0"], "targetIds": [], "label": {"text": "Caption of", "color": "#D9E4DD"}}]}